glibby/__init__.py
glibby/Auth/SPNAuthHandler.py
glibby/Auth/UserAuthHandler.py
glibby/Auth/__init__.py
glibby/Graph/Application.py
glibby/Graph/Attacks.py
glibby/Graph/GraphOperations.py
glibby/Graph/Group.py
glibby/Graph/Spn.py
glibby/Graph/User.py
glibby/Graph/__init__.py
glibby/RM/Attacks.py
glibby/RM/RMOperations.py
glibby/RM/Subscription.py
glibby/RM/__init__.py
glibby/Templates/malicious_function_app.ps1
glibby/Templates/malicious_logic_app.json
glibby/Templates/malicious_runbook_managed_identity.ps1
glibby-1.0.0.dist-info/METADATA
glibby-1.0.0.dist-info/WHEEL
glibby-1.0.0.dist-info/top_level.txt
glibby-1.0.0.dist-info/RECORD
