Metadata-Version: 2.1
Name: glibby
Version: 1.0.0
Summary: A tool written in to automate Azure attack paths.
Home-page: https://github.com/0xRoyR/Glibby
Author: Roy Rahamim (0xRoyR)
Author-email: royraham1@gmail.com
License: MIT
Classifier: Development Status :: 4 - Beta
Classifier: Intended Audience :: Developers
Classifier: Intended Audience :: System Administrators
Classifier: Intended Audience :: Information Technology
Classifier: Topic :: Security
Classifier: Topic :: Software Development :: Libraries
Classifier: Topic :: Utilities
Classifier: Topic :: Internet :: WWW/HTTP
Classifier: License :: OSI Approved :: MIT License
Classifier: Programming Language :: Python :: 3
Classifier: Programming Language :: Python :: 3.7
Classifier: Programming Language :: Python :: 3.8
Classifier: Programming Language :: Python :: 3.9
Classifier: Programming Language :: Python :: 3.10
Classifier: Programming Language :: Python :: 3.11
Classifier: Operating System :: OS Independent
Classifier: Natural Language :: English
Requires-Python: >=3.6
Requires-Dist: certifi>=2024.8.30
Requires-Dist: charset-normalizer>=3.4.0
Requires-Dist: idna>=3.10
Requires-Dist: requests>=2.32.3
Requires-Dist: urllib3>=2.2.3
